{
  "project_info": {
    "project_number": "805284952630",
    "project_id": "bio-boost",
    "storage_bucket": "bio-boost.firebasestorage.app"
  },
  "client": [
    {
      "client_info": {
        "mobilesdk_app_id": "1:805284952630:android:d2a3e8d992edbec60db697",
        "android_client_info": {
          "package_name": "com.bioboost"
        }
      },
      "oauth_client": [],
      "api_key": [
        {
          "current_key": "AIzaSyDJm3JUtnebgxPvqtQ7XMtvB6nCUCCP7Rk"
        }
      ],
      "services": {
        "appinvite_service": {
          "other_platform_oauth_client": []
        }
      }
    }
  ],
  "configuration_version": "1"
}